setup.py
pySystem/__init__.py
pySystem.egg-info/PKG-INFO
pySystem.egg-info/SOURCES.txt
pySystem.egg-info/dependency_links.txt
pySystem.egg-info/requires.txt
pySystem.egg-info/top_level.txt