Metadata-Version: 1.2
Name: pySystem
Version: 1.0.2
Summary: A simple tool to help interfacing with simple os calls
Home-page: https://github.com/joranbeasley/PySystem
Author: Joran Beasley
Author-email: joranbeasley@gmail.com
License: UNKNOWN
Platform: UNKNOWN
Classifier: Programming Language :: Python :: 3
Classifier: License :: OSI Approved :: MIT License
Classifier: Operating System :: OS Independent
Requires-Python: >=2.7
